stcli/ParseConfigTextFile.py
stcli-0.2.1.dist-info/DESCRIPTION.rst
stcli-0.2.1.dist-info/METADATA
stcli-0.2.1.dist-info/RECORD
stcli-0.2.1.dist-info/WHEEL
stcli-0.2.1.dist-info/entry_points.txt
stcli-0.2.1.dist-info/metadata.json
stcli-0.2.1.dist-info/top_level.txt
