Metadata-Version: 2.0
Name: stcli
Version: 0.2.1
Summary: This is an text parse based on CLI for config file generated by SpectrumToolset.
Home-page: UNKNOWN
Author: Yuan Chen
Author-email: huddsinyuan2014@gmail.com
License: MIT
Platform: UNKNOWN
Classifier: Development Status :: 5 - Production/Stable
Classifier: Environment :: Console
Classifier: Intended Audience :: Science/Research
Classifier: Topic :: System :: Logging
Classifier: License :: OSI Approved :: MIT License
Classifier: Operating System :: Microsoft :: Windows :: Windows 10
Classifier: Programming Language :: Python :: 3.6
Requires-Python: >=3
